{
  "champion": {
    "id": "Udyr",
    "key": "77",
    "enName": "Udyr",
    "zhName": "兽灵行者",
    "title": "乌迪尔",
    "slug": "udyr",
    "patch": "16.11.1",
    "displayName": "兽灵行者",
    "mayhemUrl": "https://arammayhem.com/zh-cn/build/udyr/"
  },
  "updatedAt": "2026-05-31T04:00:32.931Z",
  "freshness": {
    "patch": "26.11",
    "statsPatch": "26.11",
    "dataDate": "20260526",
    "sourceCount": 2,
    "championDataCount": 172,
    "patchNotesUrl": "https://www.leagueoflegends.com/en-us/news/game-updates/league-of-legends-patch-26-11-notes/"
  },
  "verdict": "兽灵行者 当前统计快照为 26.11：C 级，胜率 46.78%。下方按强化品质给出同职业装备路线。",
  "summary": {
    "tier": "C",
    "winRate": "46.78%",
    "patch": "26.11",
    "statsPatch": "26.11",
    "source": "ARAM Mayhem"
  },
  "skillOrders": [
    {
      "order": "Q>E>W",
      "pickRate": "34.72%",
      "winRate": "47.45%"
    },
    {
      "order": "Q>W>E",
      "pickRate": "25.44%",
      "winRate": "47.63%"
    },
    {
      "order": "E>Q>W",
      "pickRate": "13.56%",
      "winRate": "47.48%"
    }
  ],
  "build": {
    "starting": [
      {
        "items": [
          "影焰"
        ],
        "pickRate": "52.77%",
        "winRate": "49.52%"
      },
      {
        "items": [
          "兰德里的折磨"
        ],
        "pickRate": "48.42%",
        "winRate": "49.49%"
      },
      {
        "items": [
          "残疫"
        ],
        "pickRate": "41.07%",
        "winRate": "48.72%"
      },
      {
        "items": [
          "灭世者的死亡之帽"
        ],
        "pickRate": "36.50%",
        "winRate": "50.05%"
      },
      {
        "items": [
          "狂妄"
        ],
        "pickRate": "26.76%",
        "winRate": "42.59%"
      }
    ],
    "boots": [
      {
        "items": [
          "法师之靴"
        ],
        "pickRate": "33.88%",
        "winRate": "50.17%"
      },
      {
        "items": [
          "水银之靴"
        ],
        "pickRate": "7.90%",
        "winRate": "43.56%"
      },
      {
        "items": [
          "轻灵之靴"
        ],
        "pickRate": "1.84%",
        "winRate": "45.88%"
      },
      {
        "items": [
          "明朗之靴"
        ],
        "pickRate": "0.63%",
        "winRate": "47.36%"
      }
    ],
    "core": [
      {
        "items": [
          "残疫",
          "兰德里的折磨",
          "影焰"
        ],
        "pickRate": "12.63%",
        "winRate": "49.90%"
      },
      {
        "items": [
          "狂妄",
          "收集者",
          "无尽之刃"
        ],
        "pickRate": "6.36%",
        "winRate": "44.68%"
      },
      {
        "items": [
          "兰德里的折磨",
          "影焰",
          "灭世者的死亡之帽"
        ],
        "pickRate": "3.43%",
        "winRate": "52.20%"
      },
      {
        "items": [
          "残疫",
          "影焰",
          "灭世者的死亡之帽"
        ],
        "pickRate": "3.30%",
        "winRate": "49.57%"
      },
      {
        "items": [
          "狂妄",
          "收集者",
          "多米尼克领主的致意"
        ],
        "pickRate": "2.95%",
        "winRate": "46.76%"
      }
    ],
    "late": [
      {
        "items": [
          "幽魂面具"
        ],
        "pickRate": "3.75%",
        "winRate": "52.10%"
      },
      {
        "items": [
          "增幅典籍",
          "命定灰烬"
        ],
        "pickRate": "1.38%",
        "winRate": "52.63%"
      },
      {
        "items": [
          "爆裂魔杖",
          "遗失的章节"
        ],
        "pickRate": "5.60%",
        "winRate": "50.76%"
      },
      {
        "items": [
          "爆裂魔杖",
          "增幅典籍"
        ],
        "pickRate": "0.97%",
        "winRate": "53.22%"
      },
      {
        "items": [
          "无用大棒"
        ],
        "pickRate": "1.83%",
        "winRate": "51.59%"
      }
    ]
  },
  "augments": [
    {
      "name": "虚空裂隙",
      "tier": "棱彩",
      "winRate": "61.90%",
      "description": "用技能对敌人造成伤害时，会制造一道虚空裂痕，持续6秒，如果附近有另一道虚空裂痕，则它们会连接来对它们之间的敌人们造成75-350"
    },
    {
      "name": "珠光护手",
      "tier": "棱彩",
      "winRate": "59.00%",
      "description": "你的技能可以造成暴击，造成145%总伤害。获得25%(+ 4.5% AP)%暴击几率。"
    },
    {
      "name": "雪球扭蛋机",
      "tier": "棱彩",
      "winRate": "54.29%",
      "description": "雪球获得100技能急速。在使用雪球后，随机对自身施放一个增益型的召唤师技能并对你的目标施放一个减益型的召唤师技能。在使用雪球突进后，再次对自身施放该增益型的召唤师技能。如果你没有雪球，获得一个"
    },
    {
      "name": "最万用的瞄准镜",
      "tier": "棱彩",
      "winRate": "52.68%",
      "description": "获得300攻击距离，如果你是远程英雄则降低至150攻击距离。"
    },
    {
      "name": "飞身踢",
      "tier": "棱彩",
      "winRate": "56.54%",
      "description": "你的攻击和技能会斩杀生命值低于5%（+0.002%额外生命值）（+0.03%基础攻击力）的敌人并将目标击退，被击退的敌人在碰到其他敌人或者地形时爆炸，造成150-500(+100%额外护甲)"
    },
    {
      "name": "巨人杀手",
      "tier": "棱彩",
      "winRate": "59.69%",
      "description": "体型变小，获得30%移动速度，并基于敌方英雄体型大于你的程度造成10%到30%额外伤害。"
    },
    {
      "name": "更万用的瞄准镜",
      "tier": "金色",
      "winRate": "56.09%",
      "description": "获得200攻击距离，如果你是远程英雄则降低至100攻击距离。"
    },
    {
      "name": "质变：棱彩阶",
      "tier": "金色",
      "winRate": "66.88%",
      "description": "获得1个随机棱彩阶强化符文。"
    },
    {
      "name": "吸血习性",
      "tier": "金色",
      "winRate": "65.76%",
      "description": "你不再能够被友军治疗或获得任何生命回复。获得30%全能吸血。"
    },
    {
      "name": "超凡邪恶",
      "tier": "金色",
      "winRate": "60.68%",
      "description": "在你用技能命中敌人时永久获得1法术强度。如果是作为你的第二个强化符文，则自带40法术强度。"
    },
    {
      "name": "穿针引线",
      "tier": "金色",
      "winRate": "53.85%",
      "description": "获得@PercentPen*100@%护甲穿透和法术穿透。"
    },
    {
      "name": "易损",
      "tier": "金色",
      "winRate": "54.46%",
      "description": "你的装备效果和持续伤害效果可以暴击来造成40%额外伤害。获得20%暴击几率。"
    },
    {
      "name": "物理转魔法",
      "tier": "银色",
      "winRate": "57.22%",
      "description": "将额外攻击力转化为法术强度，并获得15%法术强度"
    },
    {
      "name": "冰寒",
      "tier": "银色",
      "winRate": "53.96%",
      "description": "你的减速效果可使移动速度降低额外的100。"
    },
    {
      "name": "扇巴掌",
      "tier": "银色",
      "winRate": "62.21%",
      "description": "每当你定身或缚地一个敌人时，获得一层可叠加的20 适应之力"
    },
    {
      "name": "万用瞄准镜",
      "tier": "银色",
      "winRate": "51.94%",
      "description": "获得100攻击距离，如果你是远程英雄则降低至50攻击距离。"
    },
    {
      "name": "俯冲轰炸",
      "tier": "银色",
      "winRate": "55.59%",
      "description": "在你阵亡时爆炸，对附近的敌人们造成目标@PercentMaxHPDamage*100@%最大生命值的真实伤害。"
    },
    {
      "name": "狂热者",
      "tier": "银色",
      "winRate": "53.20%",
      "description": "获得25%暴击率（+0.05%AP）和35%攻击速度（+0.05%AP）"
    }
  ],
  "branches": [
    {
      "name": "虚空裂隙",
      "tier": "棱彩",
      "winRate": "61.90%",
      "description": "用技能对敌人造成伤害时，会制造一道虚空裂痕，持续6秒，如果附近有另一道虚空裂痕，则它们会连接来对它们之间的敌人们造成75-350",
      "label": "技能命中/消耗流",
      "items": [
        "残疫",
        "兰德里的折磨",
        "影焰",
        "兰德里的苦楚",
        "虚空之杖"
      ],
      "reason": "强化靠技能命中或持续触发打收益。保持英雄原本的装备体系，优先选择能稳定触发、提高持续作战的补装。"
    },
    {
      "name": "珠光护手",
      "tier": "棱彩",
      "winRate": "59.00%",
      "description": "你的技能可以造成暴击，造成145%总伤害。获得25%(+ 4.5% AP)%暴击几率。",
      "label": "爆发收割流",
      "items": [
        "残疫",
        "兰德里的折磨",
        "影焰",
        "灭世者的死亡之帽",
        "虚空之杖"
      ],
      "reason": "强化提高斩杀或爆发收益。保持基础核心，补充同体系的伤害或穿透装备。"
    },
    {
      "name": "雪球扭蛋机",
      "tier": "棱彩",
      "winRate": "54.29%",
      "description": "雪球获得100技能急速。在使用雪球后，随机对自身施放一个增益型的召唤师技能并对你的目标施放一个减益型的召唤师技能。在使用雪球突进后，再次对自身施放该增益型的召唤师技能。如果你没有雪球，获得一个",
      "label": "通用强化流",
      "items": [
        "残疫",
        "兰德里的折磨",
        "影焰",
        "灭世者的死亡之帽",
        "虚空之杖"
      ],
      "reason": "没有明显改玩法时，沿用最高胜率核心出装，再根据敌方阵容补穿透或保命。"
    },
    {
      "name": "最万用的瞄准镜",
      "tier": "棱彩",
      "winRate": "52.68%",
      "description": "获得300攻击距离，如果你是远程英雄则降低至150攻击距离。",
      "label": "普攻特效流",
      "items": [
        "残疫",
        "兰德里的折磨",
        "影焰",
        "纳什之牙",
        "巫妖之祸"
      ],
      "reason": "强化把普攻价值拉高。保持英雄原本的伤害类型，补充同体系的攻速、特效或近身容错。"
    },
    {
      "name": "飞身踢",
      "tier": "棱彩",
      "winRate": "56.54%",
      "description": "你的攻击和技能会斩杀生命值低于5%（+0.002%额外生命值）（+0.03%基础攻击力）的敌人并将目标击退，被击退的敌人在碰到其他敌人或者地形时爆炸，造成150-500(+100%额外护甲)",
      "label": "爆发收割流",
      "items": [
        "残疫",
        "兰德里的折磨",
        "影焰",
        "灭世者的死亡之帽",
        "虚空之杖"
      ],
      "reason": "强化提高斩杀或爆发收益。保持基础核心，补充同体系的伤害或穿透装备。"
    },
    {
      "name": "巨人杀手",
      "tier": "棱彩",
      "winRate": "59.69%",
      "description": "体型变小，获得30%移动速度，并基于敌方英雄体型大于你的程度造成10%到30%额外伤害。",
      "label": "爆发收割流",
      "items": [
        "残疫",
        "兰德里的折磨",
        "影焰",
        "灭世者的死亡之帽",
        "虚空之杖"
      ],
      "reason": "强化提高斩杀或爆发收益。保持基础核心，补充同体系的伤害或穿透装备。"
    },
    {
      "name": "更万用的瞄准镜",
      "tier": "金色",
      "winRate": "56.09%",
      "description": "获得200攻击距离，如果你是远程英雄则降低至100攻击距离。",
      "label": "普攻特效流",
      "items": [
        "残疫",
        "兰德里的折磨",
        "影焰",
        "纳什之牙",
        "巫妖之祸"
      ],
      "reason": "强化把普攻价值拉高。保持英雄原本的伤害类型，补充同体系的攻速、特效或近身容错。"
    },
    {
      "name": "质变：棱彩阶",
      "tier": "金色",
      "winRate": "66.88%",
      "description": "获得1个随机棱彩阶强化符文。",
      "label": "通用强化流",
      "items": [
        "残疫",
        "兰德里的折磨",
        "影焰",
        "灭世者的死亡之帽",
        "虚空之杖"
      ],
      "reason": "没有明显改玩法时，沿用最高胜率核心出装，再根据敌方阵容补穿透或保命。"
    },
    {
      "name": "吸血习性",
      "tier": "金色",
      "winRate": "65.76%",
      "description": "你不再能够被友军治疗或获得任何生命回复。获得30%全能吸血。",
      "label": "生存拉扯流",
      "items": [
        "残疫",
        "兰德里的折磨",
        "影焰",
        "中娅沙漏",
        "女妖面纱"
      ],
      "reason": "强化给生存或移速收益。沿用基础核心并补容错，利用长线团战反复进出场。"
    },
    {
      "name": "超凡邪恶",
      "tier": "金色",
      "winRate": "60.68%",
      "description": "在你用技能命中敌人时永久获得1法术强度。如果是作为你的第二个强化符文，则自带40法术强度。",
      "label": "法强成长流",
      "items": [
        "残疫",
        "兰德里的折磨",
        "影焰",
        "灭世者的死亡之帽",
        "虚空之杖"
      ],
      "reason": "强化直接放大技能收益。保持基础核心，补充同体系的法强、穿透或保命装备。"
    },
    {
      "name": "穿针引线",
      "tier": "金色",
      "winRate": "53.85%",
      "description": "获得@PercentPen*100@%护甲穿透和法术穿透。",
      "label": "法强成长流",
      "items": [
        "残疫",
        "兰德里的折磨",
        "影焰",
        "灭世者的死亡之帽",
        "虚空之杖"
      ],
      "reason": "强化直接放大技能收益。保持基础核心，补充同体系的法强、穿透或保命装备。"
    },
    {
      "name": "易损",
      "tier": "金色",
      "winRate": "54.46%",
      "description": "你的装备效果和持续伤害效果可以暴击来造成40%额外伤害。获得20%暴击几率。",
      "label": "爆发收割流",
      "items": [
        "残疫",
        "兰德里的折磨",
        "影焰",
        "灭世者的死亡之帽",
        "虚空之杖"
      ],
      "reason": "强化提高斩杀或爆发收益。保持基础核心，补充同体系的伤害或穿透装备。"
    },
    {
      "name": "物理转魔法",
      "tier": "银色",
      "winRate": "57.22%",
      "description": "将额外攻击力转化为法术强度，并获得15%法术强度",
      "label": "法强成长流",
      "items": [
        "残疫",
        "兰德里的折磨",
        "影焰",
        "灭世者的死亡之帽",
        "虚空之杖"
      ],
      "reason": "强化直接放大技能收益。保持基础核心，补充同体系的法强、穿透或保命装备。"
    },
    {
      "name": "冰寒",
      "tier": "银色",
      "winRate": "53.96%",
      "description": "你的减速效果可使移动速度降低额外的100。",
      "label": "生存拉扯流",
      "items": [
        "残疫",
        "兰德里的折磨",
        "影焰",
        "中娅沙漏",
        "女妖面纱"
      ],
      "reason": "强化给生存或移速收益。沿用基础核心并补容错，利用长线团战反复进出场。"
    },
    {
      "name": "扇巴掌",
      "tier": "银色",
      "winRate": "62.21%",
      "description": "每当你定身或缚地一个敌人时，获得一层可叠加的20 适应之力",
      "label": "通用强化流",
      "items": [
        "残疫",
        "兰德里的折磨",
        "影焰",
        "灭世者的死亡之帽",
        "虚空之杖"
      ],
      "reason": "没有明显改玩法时，沿用最高胜率核心出装，再根据敌方阵容补穿透或保命。"
    },
    {
      "name": "万用瞄准镜",
      "tier": "银色",
      "winRate": "51.94%",
      "description": "获得100攻击距离，如果你是远程英雄则降低至50攻击距离。",
      "label": "普攻特效流",
      "items": [
        "残疫",
        "兰德里的折磨",
        "影焰",
        "纳什之牙",
        "巫妖之祸"
      ],
      "reason": "强化把普攻价值拉高。保持英雄原本的伤害类型，补充同体系的攻速、特效或近身容错。"
    },
    {
      "name": "俯冲轰炸",
      "tier": "银色",
      "winRate": "55.59%",
      "description": "在你阵亡时爆炸，对附近的敌人们造成目标@PercentMaxHPDamage*100@%最大生命值的真实伤害。",
      "label": "生存拉扯流",
      "items": [
        "残疫",
        "兰德里的折磨",
        "影焰",
        "中娅沙漏",
        "女妖面纱"
      ],
      "reason": "强化给生存或移速收益。沿用基础核心并补容错，利用长线团战反复进出场。"
    },
    {
      "name": "狂热者",
      "tier": "银色",
      "winRate": "53.20%",
      "description": "获得25%暴击率（+0.05%AP）和35%攻击速度（+0.05%AP）",
      "label": "爆发收割流",
      "items": [
        "残疫",
        "兰德里的折磨",
        "影焰",
        "灭世者的死亡之帽",
        "虚空之杖"
      ],
      "reason": "强化提高斩杀或爆发收益。保持基础核心，补充同体系的伤害或穿透装备。"
    }
  ],
  "caveats": [
    "海克斯大乱斗是 5v5 单线团战，强化优先服务英雄机制，而不是照搬斗魂竞技场。",
    "开局和 7/11/15 级抽到的强化会改变出装方向；同一英雄不要死套一条装备线。",
    "如果抽到的强化没有改变核心玩法，就优先采用最高登场率核心出装，再按敌方阵容补穿透或保命。"
  ],
  "sources": [
    {
      "name": "ARAM Mayhem",
      "url": "https://arammayhem.com/zh-cn/build/udyr/",
      "ok": true,
      "snippets": [
        "兽灵行者 海克斯大乱斗 26.11版本出装攻略：最佳装备、强化符文、符文配置与连招思路。C级强度，胜率 46.78%。每个版本更新。",
        "虚空裂隙 · 棱彩 · 胜率 61.90%",
        "珠光护手 · 棱彩 · 胜率 59.00%",
        "雪球扭蛋机 · 棱彩 · 胜率 54.29%"
      ]
    },
    {
      "name": "Riot 26.11 官方公告",
      "url": "https://www.leagueoflegends.com/en-us/news/game-updates/league-of-legends-patch-26-11-notes/",
      "ok": true,
      "snippets": [
        "国服当前线上版本：26.11",
        "强化推荐使用 ARAM Mayhem 当前统计快照"
      ]
    }
  ],
  "socialSearches": [
    {
      "name": "抖音",
      "url": "https://duckduckgo.com/?q=%E5%85%BD%E7%81%B5%E8%A1%8C%E8%80%85%20%E6%B5%B7%E5%85%8B%E6%96%AF%E5%A4%A7%E4%B9%B1%E6%96%97%20%E5%87%BA%E8%A3%85%20%E5%BC%BA%E5%8C%96%E7%AC%A6%E6%96%87%20site%3Adouyin.com"
    },
    {
      "name": "小红书",
      "url": "https://duckduckgo.com/?q=%E5%85%BD%E7%81%B5%E8%A1%8C%E8%80%85%20%E6%B5%B7%E5%85%8B%E6%96%AF%E5%A4%A7%E4%B9%B1%E6%96%97%20%E5%87%BA%E8%A3%85%20%E5%BC%BA%E5%8C%96%E7%AC%A6%E6%96%87%20site%3Axiaohongshu.com"
    },
    {
      "name": "B站",
      "url": "https://duckduckgo.com/?q=%E5%85%BD%E7%81%B5%E8%A1%8C%E8%80%85%20%E6%B5%B7%E5%85%8B%E6%96%AF%E5%A4%A7%E4%B9%B1%E6%96%97%20%E5%87%BA%E8%A3%85%20%E5%BC%BA%E5%8C%96%E7%AC%A6%E6%96%87%20site%3Abilibili.com"
    }
  ]
}