{
  "champion": {
    "id": "Zed",
    "key": "238",
    "enName": "Zed",
    "zhName": "影流之主",
    "title": "劫",
    "slug": "zed",
    "patch": "16.11.1",
    "displayName": "影流之主",
    "mayhemUrl": "https://arammayhem.com/zh-cn/build/zed/"
  },
  "updatedAt": "2026-05-31T04:01:10.716Z",
  "freshness": {
    "patch": "26.11",
    "statsPatch": "26.11",
    "dataDate": "20260526",
    "sourceCount": 2,
    "championDataCount": 172,
    "patchNotesUrl": "https://www.leagueoflegends.com/en-us/news/game-updates/league-of-legends-patch-26-11-notes/"
  },
  "verdict": "影流之主 当前统计快照为 26.11：A 级，胜率 51.18%。下方按强化品质给出同职业装备路线。",
  "summary": {
    "tier": "A",
    "winRate": "51.18%",
    "patch": "26.11",
    "statsPatch": "26.11",
    "source": "ARAM Mayhem"
  },
  "skillOrders": [
    {
      "order": "Q>E>W",
      "pickRate": "39.13%",
      "winRate": "51.87%"
    },
    {
      "order": "Q>W>E",
      "pickRate": "25.45%",
      "winRate": "51.74%"
    },
    {
      "order": "E>Q>W",
      "pickRate": "12.76%",
      "winRate": "51.69%"
    }
  ],
  "build": {
    "starting": [
      {
        "items": [
          "狂妄"
        ],
        "pickRate": "93.83%",
        "winRate": "52.18%"
      },
      {
        "items": [
          "公理圆弧"
        ],
        "pickRate": "78.97%",
        "winRate": "52.67%"
      },
      {
        "items": [
          "收集者"
        ],
        "pickRate": "62.21%",
        "winRate": "50.39%"
      },
      {
        "items": [
          "赛瑞尔达的怨恨"
        ],
        "pickRate": "42.36%",
        "winRate": "52.73%"
      },
      {
        "items": [
          "电震涡流剑"
        ],
        "pickRate": "32.02%",
        "winRate": "54.64%"
      }
    ],
    "boots": [
      {
        "items": [
          "明朗之靴"
        ],
        "pickRate": "28.69%",
        "winRate": "48.54%"
      },
      {
        "items": [
          "水银之靴"
        ],
        "pickRate": "7.81%",
        "winRate": "48.57%"
      },
      {
        "items": [
          "轻灵之靴"
        ],
        "pickRate": "0.27%",
        "winRate": "51.82%"
      },
      {
        "items": [
          "铁板靴"
        ],
        "pickRate": "1.25%",
        "winRate": "46.74%"
      }
    ],
    "core": [
      {
        "items": [
          "狂妄",
          "公理圆弧",
          "收集者"
        ],
        "pickRate": "15.45%",
        "winRate": "51.63%"
      },
      {
        "items": [
          "狂妄",
          "收集者",
          "公理圆弧"
        ],
        "pickRate": "14.63%",
        "winRate": "51.30%"
      },
      {
        "items": [
          "狂妄",
          "公理圆弧",
          "电震涡流剑"
        ],
        "pickRate": "6.10%",
        "winRate": "57.54%"
      },
      {
        "items": [
          "狂妄",
          "公理圆弧",
          "赛瑞尔达的怨恨"
        ],
        "pickRate": "6.03%",
        "winRate": "54.83%"
      },
      {
        "items": [
          "收集者",
          "狂妄",
          "公理圆弧"
        ],
        "pickRate": "3.67%",
        "winRate": "50.27%"
      }
    ],
    "late": [
      {
        "items": [
          "长剑",
          "守护者之刃"
        ],
        "pickRate": "3.65%",
        "winRate": "54.86%"
      },
      {
        "items": [
          "长剑",
          "锯齿短匕",
          "守护者之刃"
        ],
        "pickRate": "1.75%",
        "winRate": "55.59%"
      },
      {
        "items": [
          "长剑",
          "锯齿短匕"
        ],
        "pickRate": "26.56%",
        "winRate": "51.41%"
      },
      {
        "items": [
          "长剑",
          "考尔菲德的战锤",
          "锯齿短匕"
        ],
        "pickRate": "14.44%",
        "winRate": "51.87%"
      },
      {
        "items": [
          "长剑"
        ],
        "pickRate": "1.74%",
        "winRate": "53.41%"
      }
    ]
  },
  "augments": [
    {
      "name": "珠光护手",
      "tier": "棱彩",
      "winRate": "59.00%",
      "description": "你的技能可以造成暴击，造成145%总伤害。获得25%(+ 4.5% AP)%暴击几率。"
    },
    {
      "name": "小丑学院",
      "tier": "棱彩",
      "winRate": "57.81%",
      "description": "获得召唤师技能欺诈魔术：隐身最多3秒，并在0.125秒延迟后闪现到400单位内的目标位置。你的下一次普通攻击造成100（+150%额外AD）（+55%AP）"
    },
    {
      "name": "巨人杀手",
      "tier": "棱彩",
      "winRate": "59.69%",
      "description": "体型变小，获得30%移动速度，并基于敌方英雄体型大于你的程度造成10%到30%额外伤害。"
    },
    {
      "name": "全凭身法",
      "tier": "棱彩",
      "winRate": "50.63%",
      "description": "你的冲刺、跳跃、闪烁或传送类技能获得100技能急速。"
    },
    {
      "name": "最终形态",
      "tier": "棱彩",
      "winRate": "52.32%",
      "description": "在施放你的终极技能时，获得持续10秒的50%最大生命值护盾、20%全能吸血和30%额外移动速度"
    },
    {
      "name": "质变：混沌",
      "tier": "棱彩",
      "winRate": "59.45%",
      "description": "获得2个随机的强化符文。"
    },
    {
      "name": "升级：狂妄",
      "tier": "金色",
      "winRate": "55.62%",
      "description": "参与击杀时，【狂妄】回复你的2.5%最大生命值+ 0.5%*层数的已损失生命值，并且在增益持续时间提供10+5*层数 的移动速度。此外，获得250金币"
    },
    {
      "name": "裁决使",
      "tier": "金色",
      "winRate": "59.65%",
      "description": "对生命值低于30%的敌人们多造成10%伤害。在参与击杀后重置你的基础技能。"
    },
    {
      "name": "吸血习性",
      "tier": "金色",
      "winRate": "65.76%",
      "description": "你不再能够被友军治疗或获得任何生命回复。获得30%全能吸血。"
    },
    {
      "name": "夜狩",
      "tier": "金色",
      "winRate": "48.54%",
      "description": "在对敌人造成伤害的3秒内参与击杀该敌人会使你进入1.5秒的隐身状态。"
    },
    {
      "name": "杀戮时间到了",
      "tier": "金色",
      "winRate": "50.82%",
      "description": "在施放你的终极技能后，将所有敌人打上死亡标记。这个标记会将你对其造成的@DamageStorePercentage*100@%伤害储存起来，然后在@MarkDuration@秒后引爆，造成已储存的伤害(@Cooldown@秒冷却时间)。"
    },
    {
      "name": "质变：棱彩阶",
      "tier": "金色",
      "winRate": "66.88%",
      "description": "获得1个随机棱彩阶强化符文。"
    },
    {
      "name": "升级：收集者",
      "tier": "银色",
      "winRate": "56.26%",
      "description": "使用【收集者】的被动处决敌人时的处决阈值提升@ExecutionInc*100@%，并且提供额外@UpgradedGoldAmount@金币。获得250金币。"
    },
    {
      "name": "渴血",
      "tier": "银色",
      "winRate": "59.60%",
      "description": "获得15%全能吸血。"
    },
    {
      "name": "魔法转物理",
      "tier": "银色",
      "winRate": "54.70%",
      "description": "将法术强度转化为额外攻击力，并获得15%攻击力"
    },
    {
      "name": "残暴之力",
      "tier": "银色",
      "winRate": "50.38%",
      "description": "获得@AD@攻击力、@AbilityHaste@技能急速和@Lethality@穿甲。"
    },
    {
      "name": "炼狱龙魂",
      "tier": "银色",
      "winRate": "51.33%",
      "description": "你获得炼狱龙魂，使用技能或攻击命中敌人时造成额外伤害。"
    },
    {
      "name": "刃下生风",
      "tier": "银色",
      "winRate": "50.14%",
      "description": "从每1点固定护甲穿透和法术穿透中获得1.5移动速度"
    }
  ],
  "branches": [
    {
      "name": "珠光护手",
      "tier": "棱彩",
      "winRate": "59.00%",
      "description": "你的技能可以造成暴击，造成145%总伤害。获得25%(+ 4.5% AP)%暴击几率。",
      "label": "爆发收割流",
      "items": [
        "狂妄",
        "公理圆弧",
        "收集者",
        "无尽之刃",
        "凡性的提醒"
      ],
      "reason": "强化提高斩杀或爆发收益。保持基础核心，补充同体系的伤害或穿透装备。"
    },
    {
      "name": "小丑学院",
      "tier": "棱彩",
      "winRate": "57.81%",
      "description": "获得召唤师技能欺诈魔术：隐身最多3秒，并在0.125秒延迟后闪现到400单位内的目标位置。你的下一次普通攻击造成100（+150%额外AD）（+55%AP）",
      "label": "普攻特效流",
      "items": [
        "狂妄",
        "公理圆弧",
        "收集者",
        "破败王者之刃",
        "卢安娜的飓风"
      ],
      "reason": "强化把普攻价值拉高。保持英雄原本的伤害类型，补充同体系的攻速、特效或近身容错。"
    },
    {
      "name": "巨人杀手",
      "tier": "棱彩",
      "winRate": "59.69%",
      "description": "体型变小，获得30%移动速度，并基于敌方英雄体型大于你的程度造成10%到30%额外伤害。",
      "label": "爆发收割流",
      "items": [
        "狂妄",
        "公理圆弧",
        "收集者",
        "无尽之刃",
        "凡性的提醒"
      ],
      "reason": "强化提高斩杀或爆发收益。保持基础核心，补充同体系的伤害或穿透装备。"
    },
    {
      "name": "全凭身法",
      "tier": "棱彩",
      "winRate": "50.63%",
      "description": "你的冲刺、跳跃、闪烁或传送类技能获得100技能急速。",
      "label": "通用强化流",
      "items": [
        "狂妄",
        "公理圆弧",
        "收集者",
        "无尽之刃",
        "凡性的提醒"
      ],
      "reason": "没有明显改玩法时，沿用最高胜率核心出装，再根据敌方阵容补穿透或保命。"
    },
    {
      "name": "最终形态",
      "tier": "棱彩",
      "winRate": "52.32%",
      "description": "在施放你的终极技能时，获得持续10秒的50%最大生命值护盾、20%全能吸血和30%额外移动速度",
      "label": "生存拉扯流",
      "items": [
        "狂妄",
        "公理圆弧",
        "收集者",
        "饮血剑",
        "斯特拉克的挑战护手"
      ],
      "reason": "强化给生存或移速收益。沿用基础核心并补容错，利用长线团战反复进出场。"
    },
    {
      "name": "质变：混沌",
      "tier": "棱彩",
      "winRate": "59.45%",
      "description": "获得2个随机的强化符文。",
      "label": "通用强化流",
      "items": [
        "狂妄",
        "公理圆弧",
        "收集者",
        "无尽之刃",
        "凡性的提醒"
      ],
      "reason": "没有明显改玩法时，沿用最高胜率核心出装，再根据敌方阵容补穿透或保命。"
    },
    {
      "name": "升级：狂妄",
      "tier": "金色",
      "winRate": "55.62%",
      "description": "参与击杀时，【狂妄】回复你的2.5%最大生命值+ 0.5%*层数的已损失生命值，并且在增益持续时间提供10+5*层数 的移动速度。此外，获得250金币",
      "label": "生存拉扯流",
      "items": [
        "狂妄",
        "公理圆弧",
        "收集者",
        "饮血剑",
        "斯特拉克的挑战护手"
      ],
      "reason": "强化给生存或移速收益。沿用基础核心并补容错，利用长线团战反复进出场。"
    },
    {
      "name": "裁决使",
      "tier": "金色",
      "winRate": "59.65%",
      "description": "对生命值低于30%的敌人们多造成10%伤害。在参与击杀后重置你的基础技能。",
      "label": "爆发收割流",
      "items": [
        "狂妄",
        "公理圆弧",
        "收集者",
        "无尽之刃",
        "凡性的提醒"
      ],
      "reason": "强化提高斩杀或爆发收益。保持基础核心，补充同体系的伤害或穿透装备。"
    },
    {
      "name": "吸血习性",
      "tier": "金色",
      "winRate": "65.76%",
      "description": "你不再能够被友军治疗或获得任何生命回复。获得30%全能吸血。",
      "label": "生存拉扯流",
      "items": [
        "狂妄",
        "公理圆弧",
        "收集者",
        "饮血剑",
        "斯特拉克的挑战护手"
      ],
      "reason": "强化给生存或移速收益。沿用基础核心并补容错，利用长线团战反复进出场。"
    },
    {
      "name": "夜狩",
      "tier": "金色",
      "winRate": "48.54%",
      "description": "在对敌人造成伤害的3秒内参与击杀该敌人会使你进入1.5秒的隐身状态。",
      "label": "通用强化流",
      "items": [
        "狂妄",
        "公理圆弧",
        "收集者",
        "无尽之刃",
        "凡性的提醒"
      ],
      "reason": "没有明显改玩法时，沿用最高胜率核心出装，再根据敌方阵容补穿透或保命。"
    },
    {
      "name": "杀戮时间到了",
      "tier": "金色",
      "winRate": "50.82%",
      "description": "在施放你的终极技能后，将所有敌人打上死亡标记。这个标记会将你对其造成的@DamageStorePercentage*100@%伤害储存起来，然后在@MarkDuration@秒后引爆，造成已储存的伤害(@Cooldown@秒冷却时间)。",
      "label": "通用强化流",
      "items": [
        "狂妄",
        "公理圆弧",
        "收集者",
        "无尽之刃",
        "凡性的提醒"
      ],
      "reason": "没有明显改玩法时，沿用最高胜率核心出装，再根据敌方阵容补穿透或保命。"
    },
    {
      "name": "质变：棱彩阶",
      "tier": "金色",
      "winRate": "66.88%",
      "description": "获得1个随机棱彩阶强化符文。",
      "label": "通用强化流",
      "items": [
        "狂妄",
        "公理圆弧",
        "收集者",
        "无尽之刃",
        "凡性的提醒"
      ],
      "reason": "没有明显改玩法时，沿用最高胜率核心出装，再根据敌方阵容补穿透或保命。"
    },
    {
      "name": "升级：收集者",
      "tier": "银色",
      "winRate": "56.26%",
      "description": "使用【收集者】的被动处决敌人时的处决阈值提升@ExecutionInc*100@%，并且提供额外@UpgradedGoldAmount@金币。获得250金币。",
      "label": "通用强化流",
      "items": [
        "狂妄",
        "公理圆弧",
        "收集者",
        "无尽之刃",
        "凡性的提醒"
      ],
      "reason": "没有明显改玩法时，沿用最高胜率核心出装，再根据敌方阵容补穿透或保命。"
    },
    {
      "name": "渴血",
      "tier": "银色",
      "winRate": "59.60%",
      "description": "获得15%全能吸血。",
      "label": "生存拉扯流",
      "items": [
        "狂妄",
        "公理圆弧",
        "收集者",
        "饮血剑",
        "斯特拉克的挑战护手"
      ],
      "reason": "强化给生存或移速收益。沿用基础核心并补容错，利用长线团战反复进出场。"
    },
    {
      "name": "魔法转物理",
      "tier": "银色",
      "winRate": "54.70%",
      "description": "将法术强度转化为额外攻击力，并获得15%攻击力",
      "label": "法强成长流",
      "items": [
        "狂妄",
        "公理圆弧",
        "收集者",
        "无尽之刃",
        "凡性的提醒"
      ],
      "reason": "强化直接放大技能收益。保持基础核心，补充同体系的法强、穿透或保命装备。"
    },
    {
      "name": "残暴之力",
      "tier": "银色",
      "winRate": "50.38%",
      "description": "获得@AD@攻击力、@AbilityHaste@技能急速和@Lethality@穿甲。",
      "label": "普攻特效流",
      "items": [
        "狂妄",
        "公理圆弧",
        "收集者",
        "破败王者之刃",
        "卢安娜的飓风"
      ],
      "reason": "强化把普攻价值拉高。保持英雄原本的伤害类型，补充同体系的攻速、特效或近身容错。"
    },
    {
      "name": "炼狱龙魂",
      "tier": "银色",
      "winRate": "51.33%",
      "description": "你获得炼狱龙魂，使用技能或攻击命中敌人时造成额外伤害。",
      "label": "爆发收割流",
      "items": [
        "狂妄",
        "公理圆弧",
        "收集者",
        "无尽之刃",
        "凡性的提醒"
      ],
      "reason": "强化提高斩杀或爆发收益。保持基础核心，补充同体系的伤害或穿透装备。"
    },
    {
      "name": "刃下生风",
      "tier": "银色",
      "winRate": "50.14%",
      "description": "从每1点固定护甲穿透和法术穿透中获得1.5移动速度",
      "label": "法强成长流",
      "items": [
        "狂妄",
        "公理圆弧",
        "收集者",
        "无尽之刃",
        "凡性的提醒"
      ],
      "reason": "强化直接放大技能收益。保持基础核心，补充同体系的法强、穿透或保命装备。"
    }
  ],
  "caveats": [
    "海克斯大乱斗是 5v5 单线团战，强化优先服务英雄机制，而不是照搬斗魂竞技场。",
    "开局和 7/11/15 级抽到的强化会改变出装方向；同一英雄不要死套一条装备线。",
    "如果抽到的强化没有改变核心玩法，就优先采用最高登场率核心出装，再按敌方阵容补穿透或保命。"
  ],
  "sources": [
    {
      "name": "ARAM Mayhem",
      "url": "https://arammayhem.com/zh-cn/build/zed/",
      "ok": true,
      "snippets": [
        "影流之主 海克斯大乱斗 26.11版本出装攻略：最佳装备、强化符文、符文配置与连招思路。A级强度，胜率 51.18%。每个版本更新。",
        "珠光护手 · 棱彩 · 胜率 59.00%",
        "小丑学院 · 棱彩 · 胜率 57.81%",
        "巨人杀手 · 棱彩 · 胜率 59.69%"
      ]
    },
    {
      "name": "Riot 26.11 官方公告",
      "url": "https://www.leagueoflegends.com/en-us/news/game-updates/league-of-legends-patch-26-11-notes/",
      "ok": true,
      "snippets": [
        "国服当前线上版本：26.11",
        "强化推荐使用 ARAM Mayhem 当前统计快照"
      ]
    }
  ],
  "socialSearches": [
    {
      "name": "抖音",
      "url": "https://duckduckgo.com/?q=%E5%BD%B1%E6%B5%81%E4%B9%8B%E4%B8%BB%20%E6%B5%B7%E5%85%8B%E6%96%AF%E5%A4%A7%E4%B9%B1%E6%96%97%20%E5%87%BA%E8%A3%85%20%E5%BC%BA%E5%8C%96%E7%AC%A6%E6%96%87%20site%3Adouyin.com"
    },
    {
      "name": "小红书",
      "url": "https://duckduckgo.com/?q=%E5%BD%B1%E6%B5%81%E4%B9%8B%E4%B8%BB%20%E6%B5%B7%E5%85%8B%E6%96%AF%E5%A4%A7%E4%B9%B1%E6%96%97%20%E5%87%BA%E8%A3%85%20%E5%BC%BA%E5%8C%96%E7%AC%A6%E6%96%87%20site%3Axiaohongshu.com"
    },
    {
      "name": "B站",
      "url": "https://duckduckgo.com/?q=%E5%BD%B1%E6%B5%81%E4%B9%8B%E4%B8%BB%20%E6%B5%B7%E5%85%8B%E6%96%AF%E5%A4%A7%E4%B9%B1%E6%96%97%20%E5%87%BA%E8%A3%85%20%E5%BC%BA%E5%8C%96%E7%AC%A6%E6%96%87%20site%3Abilibili.com"
    }
  ]
}